{
  "name": "cq-spmasq",
  "version": "0.1.0",
  "author": "Chad Quilter",
  "summary": "Manages the Dnsmasq service for provisioned puppet clients.",
  "license": "Apache-2.0",
  "source": "https://github.com/chadquilter/spmasq",
  "project_page": "https://github.com/chadquilter/spmasq",
  "issues_url": "https://github.com/chadquilter/spmasq/issues",
  "tags": [
    "simp"
  ],
  "dependencies": [
    {
      "name": "simp/iptables",
      "version_requirement": ">= 6.0.1 < 7.0.0"
    },
    {
      "name": "simp/simplib",
      "version_requirement": ">= 3.3.1 < 4.0.0"
    },
    {
      "name": "puppetlabs/stdlib",
      "version_requirement": ">= 4.13.1 < 5.0.0"
    }
  ],
  "operatingsystem_support": [
    {
      "operatingsystem": "CentOS",
      "operatingsystemrelease": [
        "6",
        "7"
      ]
    },
    {
      "operatingsystem": "RedHat",
      "operatingsystemrelease": [
        "6",
        "7"
      ]
    }
  ],
  "requirements": [
    {
      "name": "puppet",
      "version_requirement": ">= 4.6.0 < 5.0.0"
    }
  ],
  "data_provider": "hiera"
}
